persontitles/__init__.py
persontitles/academic_austria.py
persontitles/academic_degrees.py
persontitles/academic_german.py
persontitles/academic_german_drtitel.py
persontitles/academic_german_wiki.py
persontitles/academic_uk.py
persontitles/academic_us.py
persontitles/gov_jobs.py
persontitles/job_titles.py
persontitles/peertitles.py
persontitles/rel_titles.py
persontitles/salutations.py
persontitles/data/__init__.py
persontitles/data/academic_austrian.txt
persontitles/data/academic_german.txt
persontitles/data/academic_german_drtitel.txt
persontitles/data/academic_german_wiki.txt
persontitles/data/academic_uk.txt
persontitles/data/academic_us.txt
persontitles/data/academic_us1.txt
persontitles/data/academic_us2.txt
persontitles/data/degrees.json
persontitles/data/english_jobtitles.txt
persontitles/data/german_jobtitles.txt
persontitles/data/nrw_ministries.txt
persontitles/data/peertitles.json
persontitles/data/salutations.txt
persontitles-0.3.9.dist-info/LICENSE
persontitles-0.3.9.dist-info/METADATA
persontitles-0.3.9.dist-info/WHEEL
persontitles-0.3.9.dist-info/top_level.txt
persontitles-0.3.9.dist-info/RECORD
