Metadata-Version: 2.1
Name: persontitles
Version: 0.3.9
Summary: Collections of academic degrees, job (and peer) titles, and salutations.
Home-page: https://github.com/0LL13/persontitles
Author: Oliver Stapel
Author-email: hardy.ecc95@gmail.com
License: MIT license
Project-URL: Bug Reports, https://github.com/0LL13/persontitles/issues
Project-URL: Source, https://github.com/0LL13/persontitles
Keywords: person,titles,degrees
Platform: UNKNOWN
Classifier: Development Status :: 2 - Pre-Alpha
Classifier: Intended Audience :: Developers
Classifier: License :: OSI Approved :: MIT License
Classifier: Natural Language :: English
Classifier: Programming Language :: Python :: Implementation :: CPython
Classifier: Operating System :: POSIX :: Linux
Classifier: Topic :: Other/Nonlisted Topic
Requires-Python: >=3.7
License-File: LICENSE
Requires-Dist: beautifulsoup4
Requires-Dist: lxml
Requires-Dist: requests
Provides-Extra: dev
Requires-Dist: check-manifest ; extra == 'dev'
Provides-Extra: test
Requires-Dist: pytest-cov ; extra == 'test'
